pfta/__init__.py
pfta/_version.py
pfta/boolean.py
pfta/cli.py
pfta/common.py
pfta/computation.py
pfta/constants.py
pfta/core.py
pfta/graphics.py
pfta/parsing.py
pfta/presentation.py
pfta/sampling.py
pfta/utilities.py
pfta/woe.py
pfta-0.4.0.dist-info/entry_points.txt
pfta-0.4.0.dist-info/licenses/LICENSE
pfta-0.4.0.dist-info/WHEEL
pfta-0.4.0.dist-info/METADATA
pfta-0.4.0.dist-info/RECORD
