Metadata-Version: 2.4
Name: pfta
Version: 0.4.0
Summary: Public Fault Tree Analyser (PFTA)
Keywords: fault tree,minimal cut sets,failure probability,failure rate
Author-email: Conway <pypi.sheep257@passmail.net>
Requires-Python: >=3.11
Classifier: Programming Language :: Python :: 3
Classifier: Programming Language :: Python :: 3.11
Classifier: Programming Language :: Python :: 3.12
Classifier: License :: OSI Approved :: GNU General Public License v3 (GPLv3)
Classifier: Operating System :: OS Independent
License-File: LICENSE
Project-URL: changelog, https://github.com/public-fta/pfta/blob/master/CHANGELOG.md
Project-URL: issues, https://github.com/public-fta/pfta/issues
Project-URL: repository, https://github.com/public-fta/pfta
